{"authorDailyContributionsMap":{"sebas-miranda":[{"date":"2026-04-08T00:00:00","commitResults":[{"hash":"e2d3d1a22ef578e86ce0e7ab81782ee2a9e9fea0","isMergeCommit":false,"messageTitle":"fix: se arreglan errores de estructura en la bitácora","messageBody":"","fileTypesAndContributionMap":{"qmd":{"insertions":13,"deletions":123}}},{"hash":"6ba13cedb9a8f53eea6b2a2d15c7e3e9be0314bc","isMergeCommit":false,"messageTitle":"docs: se agregan secciones 1.1.1, 1.1.2, 1.1.3 completas","messageBody":"","fileTypesAndContributionMap":{"qmd":{"insertions":29,"deletions":0}}},{"hash":"0e3b8e56bb29e24e1fa271336eefb7eb939211f7","isMergeCommit":false,"messageTitle":"fix: se arreglan errores de nomenclatura y de secciones duplicadas","messageBody":"","fileTypesAndContributionMap":{"qmd":{"insertions":5,"deletions":34}}},{"hash":"a0127e1e6dfbd852b7d81536639fe9a502c1ccb6","isMergeCommit":false,"messageTitle":"fix: se actualiza el pdf y html de la bitacora 1","messageBody":"","fileTypesAndContributionMap":{"tex":{"insertions":0,"deletions":14},"qmd":{"insertions":4,"deletions":3},"html":{"insertions":158,"deletions":106}}}]}],"Gabo0122":[{"date":"2026-04-02T00:00:00","commitResults":[{"hash":"17f1de8c8918319f57140dd08d9d7281300891c8","isMergeCommit":false,"messageTitle":"docs: anniade el nombre, carnet y correo","messageBody":"","fileTypesAndContributionMap":{"md":{"insertions":1,"deletions":1}}}]},{"date":"2026-04-06T00:00:00","commitResults":[{"hash":"d2f2490070a6d7b99ad5a57ad0ef69d2cfbce576","isMergeCommit":false,"messageTitle":"fix: cambio de usuario de commit","messageBody":"","fileTypesAndContributionMap":{"qmd":{"insertions":14,"deletions":0},"html":{"insertions":369,"deletions":1286}}}]}],"KevinCalderon2811":[{"date":"2026-04-01T00:00:00","commitResults":[{"hash":"e66242a764b5b60169c593eb76ba5e3d264ee223","isMergeCommit":false,"messageTitle":"feat: Limpieza y filtracion de la base inicial con los datos de Centroamerica","messageBody":"","fileTypesAndContributionMap":{"R":{"insertions":49,"deletions":2}}}]},{"date":"2026-04-02T00:00:00","commitResults":[{"hash":"2bd140737b986be1f3e492a898098ee2ad41b865","isMergeCommit":false,"messageTitle":"docs: Añadi mi informacion persopnal al README","messageBody":"","fileTypesAndContributionMap":{"md":{"insertions":1,"deletions":1}}},{"hash":"ea7a2da4faf1a8aead62387581900e8c9d37ea8f","isMergeCommit":false,"messageTitle":"docs: códigos de los países de las bases de datos de la OMS","messageBody":"","fileTypesAndContributionMap":{"country_codes":{"insertions":228,"deletions":0}}},{"hash":"32a082c03bd920e213a350acd28a51e7bc88d0b2","isMergeCommit":false,"messageTitle":"Docs: Documento que explica a detalle el contenido de las bases de datos","messageBody":"","fileTypesAndContributionMap":{}}]}],"ThePadua":[{"date":"2026-03-15T00:00:00","commitResults":[{"hash":"14b4bdc335d30445b8ce5fa24002ea65e5edd256","isMergeCommit":false,"messageTitle":"docs: Agregado plantilla quarto para presentacion de propuestas de trabajo","messageBody":"","fileTypesAndContributionMap":{"qmd":{"insertions":90,"deletions":0}}}]},{"date":"2026-03-28T00:00:00","commitResults":[{"hash":"c7b75e69a003f49154eb271623e7132aa32f97ea","isMergeCommit":false,"messageTitle":"docs: Miembros añadidos al readme","messageBody":"Updated group member details in the README.","fileTypesAndContributionMap":{"md":{"insertions":6,"deletions":5}}}]},{"date":"2026-04-05T00:00:00","commitResults":[{"hash":"f804e7b5ea753951b5899f52bb4a5180a2a3c5fc","isMergeCommit":false,"messageTitle":"docs: Se añade ensayo de primer compoenente de planificación de trabajo y se diseña en estructura de markdown con el archivo de quarto","messageBody":"","fileTypesAndContributionMap":{"qmd":{"insertions":24,"deletions":70},"html":{"insertions":3541,"deletions":0}}},{"hash":"034e7ed00cea9e162773cb9e4c168ff2fb6145b2","isMergeCommit":false,"messageTitle":"docs: Conceptualización de la idea","messageBody":"","fileTypesAndContributionMap":{"qmd":{"insertions":8,"deletions":0},"html":{"insertions":6,"deletions":0}}}]},{"date":"2026-04-06T00:00:00","commitResults":[{"hash":"20df415db2102256eeb80b611327dad66b153e7c","isMergeCommit":false,"messageTitle":"docs: Reformulacion en preguntas","messageBody":"","fileTypesAndContributionMap":{"qmd":{"insertions":99,"deletions":1},"html":{"insertions":1364,"deletions":359}}}]}]},"authorFileTypeContributionMap":{"sebas-miranda":{"html":158,"qmd":28},"Gabo0122":{"md":1,"html":1},"KevinCalderon2811":{"md":1,"R":49,"country_codes":228},"ThePadua":{"md":2,"html":3528,"qmd":27}},"authorContributionVariance":{"sebas-miranda":5974.0947,"Gabo0122":69588.945,"KevinCalderon2811":1371.1888,"ThePadua":406420.12},"authorDisplayNameMap":{"sebas-miranda":"Sebastian Josue Miranda Ramirez","Gabo0122":"Gabriel de Jesus Chaves Esquivel","KevinCalderon2811":"Kevin David Calderon Martinez","ThePadua":"Benjamin Gutierrez Padua"}}
